rkvst_simplehash/v1.py
rkvst_simplehash/v2.py
rkvst_simplehash-0.4.0.dist-info/LICENSE
rkvst_simplehash-0.4.0.dist-info/METADATA
rkvst_simplehash-0.4.0.dist-info/WHEEL
rkvst_simplehash-0.4.0.dist-info/entry_points.txt
rkvst_simplehash-0.4.0.dist-info/top_level.txt
rkvst_simplehash-0.4.0.dist-info/RECORD
