Metadata-Version: 2.1
Name: rkvst-simplehash
Version: 0.4.0
Summary: RKVST Simplehash algorithm for DLT Anchoring
Home-page: https://github.com/rkvst/rkvst-simplehash-python
Author: RKVST Inc.
Author-email: support@rkvst.com
License: MIT
Project-URL: Source, https://github.com/rkvst/rkvst-simplehash-python
Project-URL: Tracker, https://github.com/rkvst/rkvst-simplehash-python/issues
Classifier: Development Status :: 4 - Beta
Classifier: Environment :: Console
Classifier: Intended Audience :: Developers
Classifier: License :: OSI Approved :: MIT License
Classifier: Operating System :: POSIX :: Linux
Classifier: Programming Language :: Python :: 3.7
Classifier: Topic :: Utilities
Requires-Python: >=3.7
License-File: LICENSE
Requires-Dist: bencode.py (~=4.0)
Requires-Dist: requests (~=2.28)
